odoo/addons/mail_notification_with_history/README.rst
odoo/addons/mail_notification_with_history/__init__.py
odoo/addons/mail_notification_with_history/__manifest__.py
odoo/addons/mail_notification_with_history/data/mail_data.xml
odoo/addons/mail_notification_with_history/i18n/es.po
odoo/addons/mail_notification_with_history/i18n/it.po
odoo/addons/mail_notification_with_history/i18n/mail_notification_with_history.pot
odoo/addons/mail_notification_with_history/i18n/pt_BR.po
odoo/addons/mail_notification_with_history/models/__init__.py
odoo/addons/mail_notification_with_history/models/mail_message.py
odoo/addons/mail_notification_with_history/models/mail_thread.py
odoo/addons/mail_notification_with_history/readme/CONTRIBUTORS.md
odoo/addons/mail_notification_with_history/readme/CREDITS.md
odoo/addons/mail_notification_with_history/readme/DESCRIPTION.md
odoo/addons/mail_notification_with_history/readme/INSTALL.md
odoo/addons/mail_notification_with_history/static/description/icon.png
odoo/addons/mail_notification_with_history/static/description/index.html
odoo/addons/mail_notification_with_history/tests/__init__.py
odoo/addons/mail_notification_with_history/tests/test_mail_notification_with_history.py
odoo_addon_mail_notification_with_history-18.0.1.0.0.6.dist-info/METADATA
odoo_addon_mail_notification_with_history-18.0.1.0.0.6.dist-info/WHEEL
odoo_addon_mail_notification_with_history-18.0.1.0.0.6.dist-info/top_level.txt
odoo_addon_mail_notification_with_history-18.0.1.0.0.6.dist-info/RECORD
