Metadata-Version: 2.1
Name: odoo-addon-mail_notification_with_history
Version: 18.0.1.0.0.6
Requires-Python: >=3.10
Requires-Dist: odoo==18.0.*
Summary: Add the previous chatter discussion into new email notifications.
Home-page: https://github.com/OCA/social
License: AGPL-3
Author: Camptocamp, Odoo Community Association (OCA)
Author-email: support@odoo-community.org
Classifier: Programming Language :: Python
Classifier: Framework :: Odoo
Classifier: Framework :: Odoo :: 18.0
Classifier: License :: OSI Approved :: GNU Affero General Public License v3
Classifier: Development Status :: 4 - Beta
